ifb/__init__.py
ifb_wrapper-1.0.0.dist-info/LICENSE
ifb_wrapper-1.0.0.dist-info/METADATA
ifb_wrapper-1.0.0.dist-info/WHEEL
ifb_wrapper-1.0.0.dist-info/top_level.txt
ifb_wrapper-1.0.0.dist-info/RECORD
