Metadata-Version: 2.1
Name: ifb-wrapper
Version: 1.0.0
Summary: iFormBuilder API Wrapper
Home-page: UNKNOWN
Author: Jonathan Hsu
Author-email: jhsu@zerionsoftware.com
License: MIT
Platform: UNKNOWN
Requires-Python: >=3.0
Requires-Dist: pyjwt
Requires-Dist: requests
